new/include.v

`timescale 1ps/1ps
`include "CORE.v"		// processor
`include "PC.v"			// program counter
`include "IM.v"			// instruction memory
`include "IF_ID.v"		// instruction fetch / instruction decode buffer
`include "ID.v"			// instruction decode
`include "RF.v"			// register file
`include "ID_EXE.v"		// instruction decode / execute buffer
`include "EXE.v"		// execute (ALU)
`include "EXE_MEM.v"	// execute / memory buffer
`include "MEM.v"		// data memory
`include "MEM_WB.v"		// memory / write back buffer
`include "WB.v"			// write back

hdl/ID_EXE.v

module ID_EXE
#(	parameter RFW = 5,
	parameter IMW = 4,
	parameter DW = 32,
	parameter IW = 32)
(	input wire clk,
	input wire [IW-1:0] in_inst,
	input wire [DW-1:0] r1,
	input wire [DW-1:0] r2,
	output reg [DW-1:0] r1_o,
	output reg [DW-1:0] r2_o,
	output reg [IW-1:0] out_inst);

	always @(posedge clk) begin
		out_inst <= #1 in_inst;
		r1_o <= #1 r1;
		r2_o <= #1 r2;
	end


endmodule

hdl/RF.v

module RF
#(	parameter RFW = 5,
	parameter IMW = 4,
	parameter DW = 32,
	parameter IW = 32)
(
	input wire 				clk,
	//input wire 				rf_we,
	//input wire  [IW-1:0] 	alu_forward_inst,	
	//input wire  [IW-1:0] 	mem_forward_inst,	
	input wire 	[RFW-1:0]	reg1,
	input wire 	[RFW-1:0]	reg2,
	//input wire 	[RFW-1:0]	wreg,
	//input wire 	[DW-1:0]	wdata,
	//input wire 	[DW-1:0]	alu_rf_forward,
	//input wire 	[DW-1:0]	mem_rf_forward,
	output reg 	[DW-1:0] 	reg1data,
	output reg 	[DW-1:0] 	reg2data
);
	reg [DW-1:0] rf[2**RFW-1:0];
	integer i;
	
	//wire [4:0] rd_alu, rd_mem;
	//wire [6:0] opcode_alu, opcode_mem;
	
	//assign rd_alu		= alu_forward_inst[11:7 ];
	//assign opcode_alu	= alu_forward_inst[6 :0 ];
	//assign rd_mem		= mem_forward_inst[11:7 ];
	//assign opcode_mem	= mem_forward_inst[6 :0 ];
	
	always @(*) begin
		reg1data = rf[reg1];
		reg2data = rf[reg2];
		
		/*if (opcode_mem == 7'h33 | opcode_mem == 7'h13) begin
			// forwarding from the MEM stage
			if (rd_mem[RFW-1:0] == reg1[RFW-1:0])
				reg1data = mem_rf_forward;
			if (rd_mem[RFW-1:0] == reg2[RFW-1:0])
				reg2data = mem_rf_forward;
		end
		
		if (opcode_alu == 7'h33 | opcode_alu == 7'h13) begin
			// forwarding from the EXE stage
			// higher priority than MEM, because data is newer
			if (rd_alu[RFW-1:0] == reg1[RFW-1:0])
				reg1data = alu_rf_forward;
			if (rd_alu[RFW-1:0] == reg2[RFW-1:0])
				reg2data = alu_rf_forward;
		end*/
		
		if (reg1 == 0)
			reg1data = 0;
		if (reg2 == 0)
			reg2data = 0;
	end
	

	/*always @(negedge clk) begin
		if (rf_we) begin
			rf[wreg] <= #1 wdata;
		end
	end*/

	initial begin
		for (i=0;i<2**RFW;i=i+1) begin
			rf[i] <= 32'bX;
		end
	end

endmodule

new/ID.v

// R-TYPE
`define OP 		12 	//01100
// I-TYPE
`define OP_IMM 	4	//00100
`define JALR 	25	//11001
`define LOAD 	0	//00000
`define SYSTEM 	28	//11100
// S-TYPE
`define STORE 	8	//01000
// B-TYPE
`define BRANCH 	24	//11000
// U-TYPE
`define LUI 	13	//01101 
`define AUIPC 	5	//00101
// J-TYPE
`define JAL 	27	//11011

module ID 
#(	parameter RFW = 5,
	parameter IMW = 4,
	parameter DW = 32,
	parameter IW = 32)
(	input wire [IW-1:0] inst,
	output reg [RFW-1:0] addrA,
	output reg [RFW-1:0] addrB,
	output reg [DW-1:0] imm);

	wire [RFW-1:0] rs2, rs1, rd;
	wire [6:0] funct7;
	wire [6:0] opcode;
	wire [2:0] funct3;
	wire [DW-1:0] imm_I, imm_U, imm_S, imm_B, imm_J;
	
	assign imm_I	= { {20{inst[31]}}, inst[30:20] };
	assign imm_S	= { {20{inst[31]}}, inst[30:25],inst[11:7]};
	assign imm_B	= { {19{inst[31]}},inst[7],inst[30:25],inst[11:8], 1'b0};
	assign imm_U	= { {inst[31:12]}, {13{1'b0}} };
	assign imm_J	= { {11{inst[31]}}, inst[19:12],inst[20],inst[30:21], 1'b0};
	assign funct7 	= inst[31:25];
	assign rs2 		= inst[24:20];
	assign rs1		= inst[19:15];
	assign funct3	= inst[14:12];
	assign rd		= inst[11:7 ];
	assign opcode	= inst[6 :2 ];

	always @(*) begin
		if (inst[1:0] != 2'b11) begin
			$display("ERROR IN INSTRUCTION");
			$display(inst);
		end

		if 	  	(opcode == `OP) begin
			// R
			addrA = rs1;
			addrB = rs2;
			imm = 32'hX;
		end
		else if (opcode == `OP_IMM || opcode == `JALR || opcode == `LOAD || opcode == `SYSTEM) begin
			// I
			addrA = rs1;
			addrB = 32'hX;
			imm = imm_I;
		end
		else if (opcode == `STORE) begin
			// S
			addrA = rs1;
			addrB = rs2;
			imm = imm_S;
		end
		else if (opcode == `BRANCH) begin
			// B
			addrA = rs1;
			addrB = rs2;
			imm = imm_B;
		end
		else if (opcode == `LUI || opcode == `AUIPC) begin
			// U
			addrA = 32'hX;
			addrB = 32'hX;
			imm = imm_U;
		end
		else if (opcode == `JAL) begin
			// J
			addrA = 32'hX;
			addrB = 32'hX;
			imm = imm_J;
		end
	end

endmodule

new/IF_ID.v

module IF_ID
#(	parameter RFW = 5,
	parameter IMW = 4,
	parameter DW = 32,
	parameter IW = 32)
(	input wire clk,
	input wire [IW-1:0] in,
	output reg [IW-1:0] out);

	always @(posedge clk) begin
		out <= #1 in;
	end


endmodule

new/IM.v

module IM 
#(	parameter RFW = 5,
	parameter IMW = 4,
	parameter DW = 32,
	parameter IW = 32)
(	input wire [IMW-1:0] address,
	output reg [IW-1:0] out);

	integer i;
	reg [IW-1:0] im[2**IMW-1:0];

	always @(*) begin
		case (address)
			0 		: out = 32'h000006B3;
			1 		: out = 32'h0000a237;
			2 		: out = 32'h00000013;
			3 		: out = 32'h00000013;
			4 		: out = 32'h00000013;
			5 		: out = 32'h00000013;
			6 		: out = 32'h00000013;
			7 		: out = 32'h00000013;
			8 		: out = 32'h000006B3;
			9 		: out = 32'h00000013;
			10 		: out = 32'h00000013;
			11		: out = 32'h00000013;
			12		: out = 32'h00000013;
			13		: out = 32'h00000013;
			14		: out = 32'h00000013;
			15		: out = 32'h00000013;
			default : out = 32'hXX;
		endcase
	end 

	initial begin
	  // for (i=0; i<2**IMW; i=i+1)
	  //   mem[i] = 8'h00;
	  $readmemh ("IM.txt", im);
	end

endmodule

new/PC.v

module PC
#(	parameter RFW = 5,
	parameter IMW = 4,
	parameter DW = 32,
	parameter IW = 32)
(	input wire clk,
	input wire start,
	input wire [IMW-1:0] in,
	output reg [IMW-1:0] out_r);
	
	reg [IMW-1:0] out_c;

	always @(*) begin
		out_c = out_r + 1;
	end
	always @(posedge clk) begin
		out_r <= #1 out_c;
	end

	always @(posedge start) begin
		out_r <= 0;
	end

endmodule

new/CORE.v

module CORE
#(	parameter RFW = 5,
	parameter IMW = 4,
	parameter DW = 32,
	parameter IW = 32)
(	input wire clk,
	input wire start);

	reg [IMW-1:0] pc_in;
	wire [IMW-1:0] pc_out;
	wire [IW-1:0] im_inst, if_id_inst, id_exe_inst;
	wire [RFW-1:0] addrA,addrB;
	wire [DW-1:0] imm, r1, r2, r1_o, r2_o;

	PC #(.RFW(RFW),.IMW(IMW),.DW(DW),.IW(IW)) 	program_counter 	(.clk(clk),.start(start),.in(pc_in),.out_r(pc_out));
	IM #(.RFW(RFW),.IMW(IMW),.DW(DW),.IW(IW)) 	instruction_memory 	(.address(pc_out),.out(im_inst));
	IF_ID #(.RFW(RFW),.IMW(IMW),.DW(DW),.IW(IW)) if_id_buffer		(.clk(clk),.in(im_inst),.out(if_id_inst));
	ID #(.RFW(RFW),.IMW(IMW),.DW(DW),.IW(IW)) 	instruction_decode	(.inst(if_id_inst),.addrA(addrA),.addrB(addrB),.imm(imm));
	RF #(.RFW(RFW),.IMW(IMW),.DW(DW),.IW(IW)) 	register_file		(.clk(clk),.reg1(addrA),.reg2(addrB),.reg1data(r1),.reg2data(r2));
	ID_EXE #(.RFW(RFW),.IMW(IMW),.DW(DW),.IW(IW)) id_exe_buffer		(.clk(clk),.in_inst(if_id_inst),.out_inst(id_exe_inst), 
																	 .r1(r1), .r2(r2), .r1_o(r1_o), .r2_o(r2_o));



	always @(posedge start) begin
		pc_in = 0;
	end

endmodule

new/tb_CORE.v
/* 		
		CODED BY Joseph A. 
		GitHub: J-oseph
		February 20, 2022.
*/

/*
	THIS IS THE TEST BENCH. RUN SIMULATIONS FROM THIS FILE.
*/
`include "include.v"

module tb_CORE;
	reg clk;
	reg start;
	parameter RFW = 5;
	parameter IMW = 4;
	parameter DW  = 32;
	parameter IW  = 32;

	CORE #(.RFW(RFW),.IMW(IMW),.DW(DW),.IW(IW))		core(.clk(clk),.start(start));
	
	initial begin
		$dumpfile("CORE.vcd");
		$dumpvars(0, tb_CORE);

		clk = 1'b0;
		start = 1'b0;
		#1 start = 1'b1;

		#200 $display("Completed Simulation :)");
		$finish;
	end
	
	always begin
		#10 clk = ~clk;
	end
	
	


endmodule

new/CORE.vcd
$date
	Mon Sep  5 12:59:37 2022
$end
$version
	Icarus Verilog
$end
$timescale
	1ps
$end
$scope module tb_CORE $end
$var reg 1 ! clk $end
$var reg 1 " start $end
$scope module core $end
$var wire 1 ! clk $end
$var wire 1 " start $end
$var wire 32 # r2_o [31:0] $end
$var wire 32 $ r2 [31:0] $end
$var wire 32 % r1_o [31:0] $end
$var wire 32 & r1 [31:0] $end
$var wire 4 ' pc_out [3:0] $end
$var wire 32 ( imm [31:0] $end
$var wire 32 ) im_inst [31:0] $end
$var wire 32 * if_id_inst [31:0] $end
$var wire 32 + id_exe_inst [31:0] $end
$var wire 5 , addrB [4:0] $end
$var wire 5 - addrA [4:0] $end
$var reg 4 . pc_in [3:0] $end
$scope module id_exe_buffer $end
$var wire 1 ! clk $end
$var wire 32 / r2 [31:0] $end
$var wire 32 0 r1 [31:0] $end
$var wire 32 1 in_inst [31:0] $end
$var reg 32 2 out_inst [31:0] $end
$var reg 32 3 r1_o [31:0] $end
$var reg 32 4 r2_o [31:0] $end
$upscope $end
$scope module if_id_buffer $end
$var wire 1 ! clk $end
$var wire 32 5 in [31:0] $end
$var reg 32 6 out [31:0] $end
$upscope $end
$scope module instruction_decode $end
$var wire 32 7 inst [31:0] $end
$var wire 5 8 rs2 [4:0] $end
$var wire 5 9 rs1 [4:0] $end
$var wire 5 : rd [4:0] $end
$var wire 7 ; opcode [6:0] $end
$var wire 32 < imm_U [31:0] $end
$var wire 32 = imm_S [31:0] $end
$var wire 32 > imm_J [31:0] $end
$var wire 32 ? imm_I [31:0] $end
$var wire 32 @ imm_B [31:0] $end
$var wire 7 A funct7 [6:0] $end
$var wire 3 B funct3 [2:0] $end
$var reg 5 C addrA [4:0] $end
$var reg 5 D addrB [4:0] $end
$var reg 32 E imm [31:0] $end
$upscope $end
$scope module instruction_memory $end
$var wire 4 F address [3:0] $end
$var reg 32 G out [31:0] $end
$upscope $end
$scope module program_counter $end
$var wire 1 ! clk $end
$var wire 4 H in [3:0] $end
$var wire 1 " start $end
$var reg 4 I out_c [3:0] $end
$var reg 4 J out_r [3:0] $end
$upscope $end
$scope module register_file $end
$var wire 1 ! clk $end
$var wire 5 K reg1 [4:0] $end
$var wire 5 L reg2 [4:0] $end
$var reg 32 M reg1data [31:0] $end
$var reg 32 N reg2data [31:0] $end
$var integer 32 O i [31:0] $end
$upscope $end
$upscope $end
$upscope $end
$enddefinitions $end
#0
$dumpvars
b100000 O
bx N
bx M
bx L
bx K
bx J
bx I
bx H
bx G
bx F
bx E
bx D
bx C
bx B
bx A
b0xxxxxxxxxxxxxxxxxxxxxxxxxxxxxx0 @
b0xxxxxxxxxxxxxxxxxxxxxxxxxxxxxxx ?
b0xxxxxxxxxxxxxxxxxxxxxxxxxxxxxx0 >
b0xxxxxxxxxxxxxxxxxxxxxxxxxxxxxxx =
bx0000000000000 <
b0xxxxx ;
bx :
bx 9
bx 8
bx 7
bx 6
bx 5
bx 4
bx 3
bx 2
bx 1
bx 0
bx /
bx .
bx -
bx ,
bx +
bx *
bx )
bx (
bx '
bx &
bx %
bx $
bx #
0"
0!
$end
#1
b11010110011 )
b11010110011 5
b11010110011 G
b1 I
b0 '
b0 F
b0 J
b0 .
b0 H
1"
#10
1!
#11
b0 $
b0 /
b0 N
b0 &
b0 0
b0 M
b0 <
b0 ,
b0 D
b0 L
b0 -
b0 C
b0 K
b10 I
b1010001000110111 )
b1010001000110111 5
b1010001000110111 G
b0 ?
b1101 =
b100000001100 @
b0 >
b0 A
b0 8
b0 9
b0 B
b1101 :
b1100 ;
b1 '
b1 F
b1 J
b11010110011 *
b11010110011 1
b11010110011 6
b11010110011 7
#20
0!
#30
1!
#31
bx $
bx /
bx N
bx &
bx 0
bx M
b10100000000000000 <
b10100000000000000 (
b10100000000000000 E
bx ,
bx D
bx L
bx -
bx C
bx K
b100 =
b100 @
b1010000000000000 >
b1 9
b10 B
b100 :
b1101 ;
b10011 )
b10011 5
b10011 G
b11 I
b0 #
b0 4
b0 %
b0 3
b11010110011 +
b11010110011 2
b1010001000110111 *
b1010001000110111 1
b1010001000110111 6
b1010001000110111 7
b10 '
b10 F
b10 J
#40
0!
#50
1!
#51
b0 &
b0 0
b0 M
b0 <
b0 (
b0 E
b0 -
b0 C
b0 K
b100 I
b0 =
b0 @
b0 >
b0 9
b0 B
b0 :
b100 ;
b11 '
b11 F
b11 J
b10011 *
b10011 1
b10011 6
b10011 7
bx #
bx 4
bx %
bx 3
b1010001000110111 +
b1010001000110111 2
#60
0!
#70
1!
#71
b101 I
b0 %
b0 3
b10011 +
b10011 2
b100 '
b100 F
b100 J
#80
0!
#90
1!
#91
b110 I
b101 '
b101 F
b101 J
#100
0!
#110
1!
#111
b111 I
b110 '
b110 F
b110 J
#120
0!
#130
1!
#131
b1000 I
b111 '
b111 F
b111 J
#140
0!
#150
1!
#151
b11010110011 )
b11010110011 5
b11010110011 G
b1001 I
b1000 '
b1000 F
b1000 J
#160
0!
#170
1!
#171
b0 $
b0 /
b0 N
b0 &
b0 0
b0 M
bx (
bx E
b0 ,
b0 D
b0 L
b1010 I
b10011 )
b10011 5
b10011 G
b1101 =
b100000001100 @
b1101 :
b1100 ;
b1001 '
b1001 F
b1001 J
b11010110011 *
b11010110011 1
b11010110011 6
b11010110011 7
#180
0!
#190
1!
#191
bx $
bx /
bx N
b0 &
b0 0
b0 M
b0 (
b0 E
bx ,
bx D
bx L
b0 =
b0 @
b0 :
b100 ;
b1011 I
b0 #
b0 4
b11010110011 +
b11010110011 2
b10011 *
b10011 1
b10011 6
b10011 7
b1010 '
b1010 F
b1010 J
