hdl/Write_Back_Logic.v
`define RFW 5
`define DW  32
`define IW  32
module Write_Back_Logic(	
	input wire [`DW-1:0] 	in_data,		
	input wire [`IW-1:0] 		in_inst,
	input wire 		 			rf_we_e,
	output reg 	 				rf_we,
	output reg [`DW-1:0] 	wdata,
	output reg [`RFW-1:0] 	wreg
);
	wire [4:0] rd;
	wire [6:0] opcode;
	
	assign rd		= in_inst[11:7 ];
	assign opcode	= in_inst[6 :0 ];

	always @(*) begin
		rf_we = 0;
		wdata = in_data;
		
		if (opcode == 7'h33 | opcode == 7'h13) begin
			//R or I
			rf_we = 1;
			wreg = rd[`RFW-1:0];
		end
		if (wreg == 0)
			rf_we = 0;
		
		if (!rf_we_e)
			rf_we = 0;
	end


endmodule

hdl/MEM_WB.v
`define DW  32
`define IW  32
`timescale 1ps/1ps
module MEM_WB (
	input wire 			clk,	
	input wire [`DW-1:0] 	in_data,		
	input wire [`IW-1:0] in_inst,
	output reg [`DW-1:0] 	out_data,
	output reg [`IW-1:0] out_inst
);

	always @(posedge clk) begin
		out_data <= #7 in_data;
		out_inst <= #7 in_inst;
	end


endmodule

hdl/EXE_MEM.v
`define DW  32
`define IW  32
`timescale 1ps/1ps
module EXE_MEM (
	input wire 				clk,	
	input wire [`DW-1:0] in,		
	input wire [`IW-1:0] in_inst,
	output reg [`DW-1:0] out,
	output reg [`IW-1:0] out_inst
);

	always @(posedge clk) begin
		out 		<= #6 in;
		out_inst <= #6 in_inst;
	end


endmodule

hdl/ALU.v
`define DW  32
`define IW  32
module ALU (
	input  wire [`DW-1:0] in_r1,	
	input  wire [`DW-1:0] in_r2,
	input  wire [`IW-1:0] in_inst,	
	output reg  [`DW-1:0] out
);

	//R type:	funct7[6:0] rs2[4:0] rs1[4:0] funct3[2:0] rd[4:0] opcode[6:0] 7+5+5+3+5+7
	//I type:	imm[11:0] 				rs1[4:0] funct3[2:0] rd[4:0] opcode[6:0] 12 +5+3+5+7
	
	wire [6:0] 	funct7, opcode;
	wire [2:0] 	funct3;
	wire [9:0] 	R;
	wire [11:0] imm;
	wire [`DW-1:0] out_xor;
	
	assign funct7 	= in_inst[31:25];
	assign funct3	= in_inst[14:12];
	assign opcode	= in_inst[6 :0 ];
	assign imm		= in_inst[31:20];
	
	assign R = {funct3,funct7};
	assign I = funct3[2:0];
	
	//xor32 x0 (in_r1,in_r2,out_xor);
	

	always @(*) begin
		if (opcode == 7'h33) begin
			// R 
			// not included: sltu,sra,addw,subw,sllw,srlw,sraw,FP operations
			if 		(R == 10'h000)
				out = in_r1 + in_r2; 			// add
			else if 	(R == 10'h020)
				out = in_r1 - in_r2; 			// sub
			else if 	(R == 10'h100)
				out = in_r1 << in_r2; 			// sll
			else if 	(R == 10'h200)
				out = (in_r1 < in_r2) ? 1:0;	// slt
			else if 	(R == 10'h400)
				out = in_r1 + in_r2; 			// xor
			else if 	(R == 10'h500)
				out = in_r1 >> in_r2; 			// srl
			else if 	(R == 10'h600)
				out = in_r1 | in_r2; 			// or
			else if 	(R == 10'h700)
				out = in_r1 & in_r2; 			// and
			else
				out = 32'hxxxxxxxx;
		end else if (opcode == 7'h13) begin
			// I
			// not included: sltiu,srai,addiw,slliw,srliw,slaiw,ecall,ebreak,any CSRR's
			if			(I == 3'h0)
				out = in_r1 + imm; 				// addi
			else if 	(I == 3'h1 & funct7 == 7'h00)
				out = in_r1 << imm; 				// slli
			else if 	(I == 3'h2)
				out = (in_r1 < imm) ? 1:0; 	// slti
			else if 	(I == 3'h4)
				out = in_r1 ^ imm; 				// xori
			else if 	(I == 3'h5 & funct7 == 7'h00)
				out = in_r1 >> imm; 				// srli
			else if 	(I == 3'h6)
				out = in_r1 | imm; 				// ori
			else if 	(I == 3'h7)
				out = in_r1 & imm; 				// andi
			else
				out = 32'hxxxxxxxx;
		end else
				out = 32'hxxxxxxxx;
	end

endmodule

/*module xor32 (
	input  wire [`DW-1:0] a,	
	input  wire [`DW-1:0] b,	
	output wire [`DW-1:0] out
);
	integer i;
	
	for (i=0;i<DW;i=i+1) begin
		assign out[i] = a[i] ^ b[i];
	end
endmodule*/

hdl/ID_EXE.v
`define DW  32
`define IW  32
`timescale 1ps/1ps
module ID_EXE(
	input wire 				clk,	
	input wire [`DW-1:0] 		in_r1,	
	input wire [`DW-1:0] 		in_r2,
	input wire [`IW-1:0] 	in_inst,		
	output reg [`DW-1:0] 		out_r1,	
	output reg [`DW-1:0] 		out_r2,
	output reg [`IW-1:0] 	out_inst
	
);

	always @(posedge clk) begin
		out_r1 	<= #5 in_r1;
		out_r2 	<= #5 in_r2;
		out_inst <= #5 in_inst;
	end

endmodule

hdl/Register_File.v
`define RFW 5
`define DW  32
`define IW  32
`timescale 1ps/1ps
module Register_File(
	input wire 					clk,
	input wire 					rf_we,
	input wire 					rf_reset,
	input wire  [`IW-1:0] 	alu_forward_inst,	
	input wire  [`IW-1:0] 	mem_forward_inst,	
	input wire 	[`RFW-1:0]	reg1,
	input wire 	[`RFW-1:0]	reg2,
	input wire 	[`RFW-1:0]	wreg,
	input wire 	[`DW-1:0]	wdata,
	input wire 	[`DW-1:0]	alu_rf_forward,
	input wire 	[`DW-1:0]	mem_rf_forward,
	output reg 	[`DW-1:0] 	reg1data,
	output reg 	[`DW-1:0] 	reg2data
);
	integer i;
	reg [`DW-1:0] rf[2**`RFW-1:0];
	
	wire [4:0] rd_alu, rd_mem;
	wire [6:0] opcode_alu, opcode_mem;
	
	assign rd_alu		= alu_forward_inst[11:7 ];
	assign opcode_alu	= alu_forward_inst[6 :0 ];
	assign rd_mem		= mem_forward_inst[11:7 ];
	assign opcode_mem	= mem_forward_inst[6 :0 ];
	
	always @(*) begin
		reg1data = rf[reg1];
		reg2data = rf[reg2];
		
		if (opcode_mem == 7'h33 | opcode_mem == 7'h13) begin
			// forwarding from the MEM stage
			if (rd_mem[`RFW-1:0] == reg1[`RFW-1:0])
				reg1data = mem_rf_forward;
			if (rd_mem[`RFW-1:0] == reg2[`RFW-1:0])
				reg2data = mem_rf_forward;
		end
		
		if (opcode_alu == 7'h33 | opcode_alu == 7'h13) begin
			// forwarding from the EXE stage
			// higher priority than MEM, because data is newer
			if (rd_alu[`RFW-1:0] == reg1[`RFW-1:0])
				reg1data = alu_rf_forward;
			if (rd_alu[`RFW-1:0] == reg2[`RFW-1:0])
				reg2data = alu_rf_forward;
		end
		
		if (reg1 == 0)
			reg1data = 0;
		if (reg2 == 0)
			reg2data = 0;
	end
	

	always @(negedge clk) begin
		if (rf_reset) begin
			for (i=0;i<2**`RFW;i=i+1) begin
				rf[i] <= #3 0;
			end
		end
		else
			if (rf_we)
				rf[wreg] <= #3 wdata;
	end

endmodule

hdl/Instruction_Decode.v
`define RFW 5
`define IW  32
module Instruction_Decode (
	input  wire [`IW-1:0]		in_inst,
	output reg  [`RFW-1:0]	reg1,
	output reg  [`RFW-1:0]	reg2
);

	//R type:	funct7[6:0] rs2[4:0] rs1[4:0] funct3[2:0] rd[4:0] opcode[6:0] 7+5+5+3+5+7
	//I type:	imm[11:0] 				rs1[4:0] funct3[2:0] rd[4:0] opcode[6:0] 12 +5+3+5+7
	
	wire [4:0] rs2, rs1, rd;
	wire [6:0] funct7, opcode;
	wire [2:0] funct3;
	wire [11:0] imm;
	
	assign funct7 	= in_inst[31:25];
	assign rs2 		= in_inst[24:20];
	assign rs1		= in_inst[19:15];
	assign funct3	= in_inst[14:12];
	assign rd		= in_inst[11:7 ];
	assign opcode	= in_inst[6 :0 ];
	
	assign imm		= in_inst[31:20];
	
	always @(*) begin
		if (opcode == 7'h33 | opcode == 7'h3A) begin
			// R
			reg1 	= rs1[`RFW-1:0];
			reg2 	= rs2[`RFW-1:0];
		end
		else if (opcode == 7'h03 | opcode == 7'h0F | opcode == 7'h13 | opcode == 7'h1B) begin
			// I
			reg1 = rs1[`RFW-1:0];
			reg2 = rs1[`RFW-1:0]; // don't care, but will assign to the same reg
			
		end else begin
			reg1 = 32'bx;
			reg2 = 32'bx;
		end
	end

endmodule

hdl/IF_ID.v
`define IW  32
`timescale 1ps/1ps
module IF_ID (
	input wire 			clk,	
	input wire [`IW-1:0] in,	
	output reg [`IW-1:0] out
);

	always @(posedge clk) begin
		out <= #2 in;
	end

endmodule

hdl/Instruction_Mem.v
`define IMW 4
`define IW  32
module Instruction_Mem 
  (input  wire [`IMW-1:0] 	address,
	input	 wire					im_cs,
	output reg  [`IW-1:0]	im_out
	);
	// r1 r2 wr rfe x
	//reg [7:0] ram[3:0];
	
	always @(*) begin
		if (!im_cs)
			im_out = 32'h00;
		else begin
			case (address)
				0 			: im_out = 32'h000046B3;
				1 			: im_out = 32'h00004633;
				2 			: im_out = 32'h000045B3;
				3 			: im_out = 32'h01458593;
				4 			: im_out = 32'h06558613;
				5 			: im_out = 32'h40B606B3;
				6 			: im_out = 32'h00D60733;
				7 			: im_out = 32'h00361793;
				8 			: im_out = 32'h00F00033;
				9 			: im_out = 32'h00000013;
				10 		: im_out = 32'h00000013;
				11			: im_out = 32'h00000013;
				12			: im_out = 32'h00000013;
				13			: im_out = 32'h00000013;
				14			: im_out = 32'h00000013;
				15			: im_out = 32'h00000013;
				default 	: im_out = 32'hXX;
			endcase
		end
	end
	
endmodule

hdl/Program_Counter.v
`timescale 1ps/1ps
`define IMW 4
module Program_Counter (
	input  wire 		clk,
	input  wire [`IMW-1:0] in,
	output reg  [`IMW-1:0] out
);
	always @(posedge clk) begin
		out <= #1 in;
	end
	
endmodule

hdl/RISC.v
`define RFW 5
`define IMW 4
`define DW  32
`define IW  32
module RISC(
	input  wire 				clk,
	input  wire [`IMW-1:0]	pc_in,
	input	 wire					im_cs,
	input	 wire					rf_we_e,
	input	 wire					rf_reset,
	output wire [`IMW-1:0] 	pc_out,
	output wire [`IW-1:0] 	if_id_out,
	output wire [`DW-1:0] 	id_exe_r1,
	output wire [`DW-1:0] 	id_exe_r2,
	output wire [`DW-1:0] 	exe_mem_out,
	output wire [`DW-1:0] 	mem_wb_out
	/*/////////// KEY //////////
	input 		     [1:0]		KEY,

	//////////// LED //////////
	output		     [9:0]		LEDR,

	//////////// SW //////////
	input 		     [9:0]		SW*/
);
	wire [`IW-1:0] 	im_out, id_exe_out_inst, exe_mem_inst, mem_wb_inst;
	wire [`DW-1:0] 	wdata, rf_r1, rf_r2, alu_out;
	wire [`RFW-1:0] 	reg1, reg2, wreg;
	
	Program_Counter pc0		(.clk(clk), .in(pc_in), .out(pc_out));
	
	Instruction_Mem im0		(.address(pc_out), .im_cs(im_cs), .im_out(im_out));
	
	IF_ID IF_ID0				(.clk(clk), .in(im_out), .out(if_id_out));
	
	Instruction_Decode id0	(.in_inst(if_id_out), .reg1(reg1), .reg2(reg2));
	
	Register_File rf0			(.clk(clk), .rf_we(rf_we), .rf_reset(rf_reset), .alu_forward_inst(id_exe_out_inst), .mem_forward_inst(exe_mem_inst), .reg1(reg1), .reg2(reg2), .wreg(wreg), .wdata(wdata), .alu_rf_forward(alu_out), .mem_rf_forward(exe_mem_out), .reg1data(rf_r1), .reg2data(rf_r2));
									 
	ID_EXE id_exe0				(.clk(clk), .in_r1(rf_r1), .in_r2(rf_r2), .in_inst(if_id_out), .out_r1(id_exe_r1), .out_r2(id_exe_r2), .out_inst(id_exe_out_inst));
	
	ALU alu0						(.in_r1(id_exe_r1), .in_r2(id_exe_r2), .in_inst(id_exe_out_inst), .out(alu_out));
	
	EXE_MEM exe_mem0			(.clk(clk), .in(alu_out), .in_inst(id_exe_out_inst), .out(exe_mem_out), .out_inst(exe_mem_inst));
	
	MEM_WB mem_wb0				(.clk(clk), .in_data(exe_mem_out), .in_inst(exe_mem_inst), .out_data(mem_wb_out), .out_inst(mem_wb_inst));
	
	Write_Back_Logic wbl0	(.in_data(mem_wb_out), .in_inst(mem_wb_inst), .rf_we_e(rf_we_e), .rf_we(rf_we), .wdata(wdata), .wreg(wreg));
	
endmodule














	/*//////////// CLOCK //////////
	input 		          		ADC_CLK_10,
	input 		          		MAX10_CLK1_50,
	input 		          		MAX10_CLK2_50,

	///////////// SDRAM //////////
	output		    [12:0]		DRAM_ADDR,
	output		     [1:0]		DRAM_BA,
	output		          		DRAM_CAS_N,
	output		          		DRAM_CKE,
	output		          		DRAM_CLK,
	output		          		DRAM_CS_N,
	inout 		    [15:0]		DRAM_DQ,
	output		          		DRAM_LDQM,
	output		          		DRAM_RAS_N,
	output		          		DRAM_UDQM,
	output		          		DRAM_WE_N,

	//////////// SEG7 //////////
	output		     [7:0]		HEX0,
	output		     [7:0]		HEX1,
	output		     [7:0]		HEX2,
	output		     [7:0]		HEX3,
	output		     [7:0]		HEX4,
	output		     [7:0]		HEX5,*/
	/*/////////// VGA //////////
	output		     [3:0]		VGA_B,
	output		     [3:0]		VGA_G,
	output		          		VGA_HS,
	output		     [3:0]		VGA_R,
	output		          		VGA_VS,

	//////////// Accelerometer //////////
	output		          		GSENSOR_CS_N,
	input 		     [2:1]		GSENSOR_INT,
	output		          		GSENSOR_SCLK,
	inout 		          		GSENSOR_SDI,
	inout 		          		GSENSOR_SDO,

	//////////// Arduino //////////
	inout 		    [15:0]		ARDUINO_IO,
	inout 		          		ARDUINO_RESET_N*/

tb/tb_RISC.v
/* 		
		CODED BY Joseph A. 
		GitHub: J-oseph
		February 20, 2022.
*/

/*
	THIS IS THE TEST BENCH. RUN SIMULATIONS FROM THIS FILE.
*/

`define RFW 5
`define IMW 4
`define DW  32
`define IW  32
`timescale 1ps/1ps
module tb_RISC;
	wire  [`IMW-1:0]	pc_in;
	wire  [`IMW-1:0]	pc_out;
	wire  [`IW-1:0]	if_id_out;
	wire  [`DW-1:0]	id_exe_r1;
	wire  [`DW-1:0]	id_exe_r2;
	wire  [`DW-1:0]	exe_mem_out;
	wire  [`DW-1:0]	mem_wb_out;
	wire  				im_cs;
	wire 		  			rf_reset;
	reg 		  			rf_res;
	reg 		  			rf_writeenable;
	reg		  			clk;
	reg  	[`IMW-1:0]	pc_input;
	reg  					im_chipselect;
	 
	assign pc_in  		= pc_input [`IMW-1:0];
	assign im_cs  		= im_chipselect;
	assign rf_reset  	= rf_res;
	assign rf_we  		= rf_writeenable;
	
	

	RISC risc0(	.clk(clk), 					.pc_in(pc_in), 				.im_cs(im_cs), 				.rf_we_e(rf_we), 
					.rf_reset(rf_reset),		.pc_out(pc_out), 				.if_id_out(if_id_out), 		.id_exe_r1(id_exe_r1),
					.id_exe_r2(id_exe_r2),	.exe_mem_out(exe_mem_out), .mem_wb_out(mem_wb_out));
	
	initial begin
		clk = 0;
		rf_writeenable = 0;
		pc_input = 0;
		im_chipselect = 1;
		rf_res = 1;
		#51 rf_res = 0;
		
		#49 pc_input = pc_input + 1;
		#100 pc_input = pc_input + 1;
		#100 pc_input = pc_input + 1;
		#100 pc_input = pc_input + 1;
		#45  rf_writeenable = 1;
		#55  pc_input = pc_input + 1;
		repeat(32) begin
			#100 pc_input = pc_input + 1;
		end
			
		//$finish;
	end
	
	always begin
		#50 clk = ~clk;
	end
	
	


endmodule

hdl/RISC.vcd
$date
	Sat Aug 13 16:34:06 2022
$end
$version
	Icarus Verilog
$end
$timescale
	1ps
$end
$scope module tb_RISC $end
$var wire 1 ! im_cs $end
$var wire 4 " pc_in [3:0] $end
$var wire 1 # rf_reset $end
$var wire 1 $ rf_we $end
$var wire 4 % pc_out [3:0] $end
$var wire 32 & mem_wb_out [31:0] $end
$var wire 32 ' if_id_out [31:0] $end
$var wire 32 ( id_exe_r2 [31:0] $end
$var wire 32 ) id_exe_r1 [31:0] $end
$var wire 32 * exe_mem_out [31:0] $end
$var reg 1 + clk $end
$var reg 1 , im_chipselect $end
$var reg 4 - pc_input [3:0] $end
$var reg 1 . rf_res $end
$var reg 1 / rf_writeenable $end
$scope module risc0 $end
$var wire 1 + clk $end
$var wire 1 ! im_cs $end
$var wire 4 0 pc_in [3:0] $end
$var wire 1 # rf_reset $end
$var wire 1 $ rf_we_e $end
$var wire 5 1 wreg [4:0] $end
$var wire 32 2 wdata [31:0] $end
$var wire 1 3 rf_we $end
$var wire 32 4 rf_r2 [31:0] $end
$var wire 32 5 rf_r1 [31:0] $end
$var wire 5 6 reg2 [4:0] $end
$var wire 5 7 reg1 [4:0] $end
$var wire 4 8 pc_out [3:0] $end
$var wire 32 9 mem_wb_out [31:0] $end
$var wire 32 : mem_wb_inst [31:0] $end
$var wire 32 ; im_out [31:0] $end
$var wire 32 < if_id_out [31:0] $end
$var wire 32 = id_exe_r2 [31:0] $end
$var wire 32 > id_exe_r1 [31:0] $end
$var wire 32 ? id_exe_out_inst [31:0] $end
$var wire 32 @ exe_mem_out [31:0] $end
$var wire 32 A exe_mem_inst [31:0] $end
$var wire 32 B alu_out [31:0] $end
$scope module IF_ID0 $end
$var wire 1 + clk $end
$var wire 32 C in [31:0] $end
$var reg 32 D out [31:0] $end
$upscope $end
$scope module alu0 $end
$var wire 7 E opcode [6:0] $end
$var wire 32 F in_r2 [31:0] $end
$var wire 32 G in_r1 [31:0] $end
$var wire 32 H in_inst [31:0] $end
$var wire 12 I imm [11:0] $end
$var wire 7 J funct7 [6:0] $end
$var wire 3 K funct3 [2:0] $end
$var wire 10 L R [9:0] $end
$var wire 1 M I $end
$var reg 32 N out [31:0] $end
$upscope $end
$scope module exe_mem0 $end
$var wire 1 + clk $end
$var wire 32 O in [31:0] $end
$var wire 32 P in_inst [31:0] $end
$var reg 32 Q out [31:0] $end
$var reg 32 R out_inst [31:0] $end
$upscope $end
$scope module id0 $end
$var wire 32 S in_inst [31:0] $end
$var wire 5 T rs2 [4:0] $end
$var wire 5 U rs1 [4:0] $end
$var wire 5 V rd [4:0] $end
$var wire 7 W opcode [6:0] $end
$var wire 12 X imm [11:0] $end
$var wire 7 Y funct7 [6:0] $end
$var wire 3 Z funct3 [2:0] $end
$var reg 5 [ reg1 [4:0] $end
$var reg 5 \ reg2 [4:0] $end
$upscope $end
$scope module id_exe0 $end
$var wire 1 + clk $end
$var wire 32 ] in_inst [31:0] $end
$var wire 32 ^ in_r2 [31:0] $end
$var wire 32 _ in_r1 [31:0] $end
$var reg 32 ` out_inst [31:0] $end
$var reg 32 a out_r1 [31:0] $end
$var reg 32 b out_r2 [31:0] $end
$upscope $end
$scope module im0 $end
$var wire 1 ! im_cs $end
$var wire 4 c address [3:0] $end
$var reg 32 d im_out [31:0] $end
$upscope $end
$scope module mem_wb0 $end
$var wire 1 + clk $end
$var wire 32 e in_data [31:0] $end
$var wire 32 f in_inst [31:0] $end
$var reg 32 g out_data [31:0] $end
$var reg 32 h out_inst [31:0] $end
$upscope $end
$scope module pc0 $end
$var wire 1 + clk $end
$var wire 4 i in [3:0] $end
$var reg 4 j out [3:0] $end
$upscope $end
$scope module rf0 $end
$var wire 32 k alu_forward_inst [31:0] $end
$var wire 32 l alu_rf_forward [31:0] $end
$var wire 1 + clk $end
$var wire 32 m mem_forward_inst [31:0] $end
$var wire 32 n mem_rf_forward [31:0] $end
$var wire 5 o reg1 [4:0] $end
$var wire 5 p reg2 [4:0] $end
$var wire 1 # rf_reset $end
$var wire 5 q wreg [4:0] $end
$var wire 32 r wdata [31:0] $end
$var wire 1 3 rf_we $end
$var wire 5 s rd_mem [4:0] $end
$var wire 5 t rd_alu [4:0] $end
$var wire 7 u opcode_mem [6:0] $end
$var wire 7 v opcode_alu [6:0] $end
$var reg 32 w reg1data [31:0] $end
$var reg 32 x reg2data [31:0] $end
$var integer 32 y i [31:0] $end
$upscope $end
$scope module wbl0 $end
$var wire 32 z in_data [31:0] $end
$var wire 32 { in_inst [31:0] $end
$var wire 1 $ rf_we_e $end
$var wire 5 | rd [4:0] $end
$var wire 7 } opcode [6:0] $end
$var reg 1 3 rf_we $end
$var reg 32 ~ wdata [31:0] $end
$var reg 5 !" wreg [4:0] $end
$upscope $end
$upscope $end
$upscope $end
$enddefinitions $end
#0
$dumpvars
bx !"
bx ~
bx }
bx |
bx {
bx z
b100000 y
bx x
bx w
bx v
bx u
bx t
bx s
bx r
bx q
bx p
bx o
bx n
bx m
bx l
bx k
bx j
b0 i
bx h
bx g
bx f
bx e
bx d
bx c
bx b
bx a
bx `
bx _
bx ^
bx ]
bx \
bx [
bx Z
bx Y
bx X
bx W
bx V
bx U
bx T
bx S
bx R
bx Q
bx P
bx O
bx N
xM
bx L
bx K
bx J
bx I
bx H
bx G
bx F
bx E
bx D
bx C
bx B
bx A
bx @
bx ?
bx >
bx =
bx <
bx ;
bx :
bx 9
bx 8
bx 7
bx 6
bx 5
bx 4
03
bx 2
bx 1
b0 0
0/
1.
b0 -
1,
0+
bx *
bx )
bx (
bx '
bx &
bx %
0$
1#
b0 "
1!
$end
#10
1+
#11
b100011010110011 ;
b100011010110011 C
b100011010110011 d
b0 %
b0 8
b0 c
b0 j
#20
b100000 y
0+
#30
1+
#32
b0 4
b0 ^
b0 x
b0 5
b0 _
b0 w
b0 6
b0 \
b0 p
b0 7
b0 [
b0 o
b0 Y
b0 T
b0 U
b100 Z
b1101 V
b110011 W
b0 X
b100011010110011 '
b100011010110011 <
b100011010110011 D
b100011010110011 S
b100011010110011 ]
#40
b100000 y
0+
#50
1+
#51
0#
0.
#55
0M
b0 B
b0 N
b0 O
b0 l
b1101 t
b110011 v
b0 I
b110011 E
b100 K
b1000000000 L
b0 J
b100011010110011 ?
b100011010110011 H
b100011010110011 P
b100011010110011 `
b100011010110011 k
b0 (
b0 =
b0 F
b0 b
b0 )
b0 >
b0 G
b0 a
#60
0+
#70
1+
#76
b1101 s
b110011 u
b100011010110011 A
b100011010110011 R
b100011010110011 f
b100011010110011 m
b0 *
b0 @
b0 Q
b0 e
b0 n
#80
0+
#90
1+
#97
b1101 1
b1101 q
b1101 !"
03
b1101 |
b110011 }
b0 2
b0 r
b0 ~
b100011010110011 :
b100011010110011 h
b100011010110011 {
b0 &
b0 9
b0 g
b0 z
#100
0+
b1 "
b1 0
b1 i
b1 -
#110
1+
#111
b100011000110011 ;
b100011000110011 C
b100011000110011 d
b1 %
b1 8
b1 c
b1 j
#120
0+
#130
1+
#132
b1100 V
b100011000110011 '
b100011000110011 <
b100011000110011 D
b100011000110011 S
b100011000110011 ]
#140
0+
#150
1+
#155
b1100 t
b100011000110011 ?
b100011000110011 H
b100011000110011 P
b100011000110011 `
b100011000110011 k
#160
0+
#170
1+
#176
b1100 s
b100011000110011 A
b100011000110011 R
b100011000110011 f
b100011000110011 m
#180
0+
#190
1+
#197
b1100 1
b1100 q
b1100 !"
03
b1100 |
b100011000110011 :
b100011000110011 h
b100011000110011 {
#200
0+
b10 "
b10 0
b10 i
b10 -
#210
1+
#211
b100010110110011 ;
b100010110110011 C
b100010110110011 d
b10 %
b10 8
b10 c
b10 j
#220
0+
#230
1+
#232
b1011 V
b100010110110011 '
b100010110110011 <
b100010110110011 D
b100010110110011 S
b100010110110011 ]
#240
0+
#250
1+
#255
b1011 t
b100010110110011 ?
b100010110110011 H
b100010110110011 P
b100010110110011 `
b100010110110011 k
#260
0+
#270
1+
#276
b1011 s
b100010110110011 A
b100010110110011 R
b100010110110011 f
b100010110110011 m
#280
0+
#290
1+
#297
b1011 1
b1011 q
b1011 !"
03
b1011 |
b100010110110011 :
b100010110110011 h
b100010110110011 {
#300
0+
b11 "
b11 0
b11 i
b11 -
#310
1+
#311
b1010001011000010110010011 ;
b1010001011000010110010011 C
b1010001011000010110010011 d
b11 %
b11 8
b11 c
b11 j
#320
0+
#330
1+
#332
b1011 6
b1011 \
b1011 p
b1011 7
b1011 [
b1011 o
b10100 T
b1011 U
b0 Z
b10011 W
b10100 X
b1010001011000010110010011 '
b1010001011000010110010011 <
b1010001011000010110010011 D
b1010001011000010110010011 S
b1010001011000010110010011 ]
#340
0+
#350
1+
#355
b10100 4
b10100 ^
b10100 x
b10100 5
b10100 _
b10100 w
b10100 B
b10100 N
b10100 O
b10100 l
b10011 v
b10100 I
b10011 E
b0 L
b0 K
b1010001011000010110010011 ?
b1010001011000010110010011 H
b1010001011000010110010011 P
b1010001011000010110010011 `
b1010001011000010110010011 k
#360
0+
#370
1+
#375
b101000 4
b101000 ^
b101000 x
b101000 5
b101000 _
b101000 w
b101000 B
b101000 N
b101000 O
b101000 l
b10100 (
b10100 =
b10100 F
b10100 b
b10100 )
b10100 >
b10100 G
b10100 a
#376
b10011 u
b101000 4
b101000 ^
b101000 x
b101000 5
b101000 _
b101000 w
b1010001011000010110010011 A
b1010001011000010110010011 R
b1010001011000010110010011 f
b1010001011000010110010011 m
b10100 *
b10100 @
b10100 Q
b10100 e
b10100 n
#380
0+
#390
1+
#395
b111100 4
b111100 ^
b111100 x
b111100 5
b111100 _
b111100 w
b111100 B
b111100 N
b111100 O
b111100 l
b101000 (
b101000 =
b101000 F
b101000 b
b101000 )
b101000 >
b101000 G
b101000 a
#396
b111100 4
b111100 ^
b111100 x
b111100 5
b111100 _
b111100 w
b101000 *
b101000 @
b101000 Q
b101000 e
b101000 n
#397
b10011 }
03
b10100 2
b10100 r
b10100 ~
b1010001011000010110010011 :
b1010001011000010110010011 h
b1010001011000010110010011 {
b10100 &
b10100 9
b10100 g
b10100 z
#400
0+
b100 "
b100 0
b100 i
b100 -
#410
1+
#411
b110010101011000011000010011 ;
b110010101011000011000010011 C
b110010101011000011000010011 d
b100 %
b100 8
b100 c
b100 j
#415
b1010000 4
b1010000 ^
b1010000 x
b1010000 5
b1010000 _
b1010000 w
b1010000 B
b1010000 N
b1010000 O
b1010000 l
b111100 (
b111100 =
b111100 F
b111100 b
b111100 )
b111100 >
b111100 G
b111100 a
#416
b1010000 4
b1010000 ^
b1010000 x
b1010000 5
b1010000 _
b1010000 w
b111100 *
b111100 @
b111100 Q
b111100 e
b111100 n
#417
03
b101000 2
b101000 r
b101000 ~
b101000 &
b101000 9
b101000 g
b101000 z
#420
0+
#430
1+
#432
b11 Y
b101 T
b1100 V
b1100101 X
b110010101011000011000010011 '
b110010101011000011000010011 <
b110010101011000011000010011 D
b110010101011000011000010011 S
b110010101011000011000010011 ]
#435
b1100100 4
b1100100 ^
b1100100 x
b1100100 5
b1100100 _
b1100100 w
b1100100 B
b1100100 N
b1100100 O
b1100100 l
b1010000 (
b1010000 =
b1010000 F
b1010000 b
b1010000 )
b1010000 >
b1010000 G
b1010000 a
#436
b1100100 4
b1100100 ^
b1100100 x
b1100100 5
b1100100 _
b1100100 w
b1010000 *
b1010000 @
b1010000 Q
b1010000 e
b1010000 n
#437
03
b111100 2
b111100 r
b111100 ~
b111100 &
b111100 9
b111100 g
b111100 z
#440
0+
#445
13
1$
1/
#450
1+
#455
b1010000 4
b1010000 ^
b1010000 x
b1010000 5
b1010000 _
b1010000 w
b1100 t
b1100101 I
b11 L
b11 J
b11001001 B
b11001001 N
b11001001 O
b11001001 l
b110010101011000011000010011 ?
b110010101011000011000010011 H
b110010101011000011000010011 P
b110010101011000011000010011 `
b110010101011000011000010011 k
b1100100 (
b1100100 =
b1100100 F
b1100100 b
b1100100 )
b1100100 >
b1100100 G
b1100100 a
#456
b1100100 4
b1100100 ^
b1100100 x
b1100100 5
b1100100 _
b1100100 w
b1100100 *
b1100100 @
b1100100 Q
b1100100 e
b1100100 n
#457
b1010000 2
b1010000 r
b1010000 ~
13
b1010000 &
b1010000 9
b1010000 g
b1010000 z
#460
0+
#463
b1100100 4
b1100100 ^
b1100100 x
b1100100 5
b1100100 _
b1100100 w
#470
1+
#476
b1100 s
b1010000 4
b1010000 ^
b1010000 x
b1010000 5
b1010000 _
b1010000 w
b110010101011000011000010011 A
b110010101011000011000010011 R
b110010101011000011000010011 f
b110010101011000011000010011 m
b11001001 *
b11001001 @
b11001001 Q
b11001001 e
b11001001 n
#477
b1100100 2
b1100100 r
b1100100 ~
13
b1100100 &
b1100100 9
b1100100 g
b1100100 z
#480
0+
#483
b1100100 4
b1100100 ^
b1100100 x
b1100100 5
b1100100 _
b1100100 w
#490
1+
#497
b1100 1
b1100 q
b1100 !"
b1100 |
b11001001 2
b11001001 r
b11001001 ~
13
b110010101011000011000010011 :
b110010101011000011000010011 h
b110010101011000011000010011 {
b11001001 &
b11001001 9
b11001001 g
b11001001 z
#500
0+
b101 "
b101 0
b101 i
b101 -
#510
1+
#511
b1000000101101100000011010110011 ;
b1000000101101100000011010110011 C
b1000000101101100000011010110011 d
b101 %
b101 8
b101 c
b101 j
#520
0+
#530
1+
#532
b11001001 5
b11001001 _
b11001001 w
b1100 7
b1100 [
b1100 o
b100000 Y
b1011 T
b1100 U
b1101 V
b110011 W
b10000001011 X
b1000000101101100000011010110011 '
b1000000101101100000011010110011 <
b1000000101101100000011010110011 D
b1000000101101100000011010110011 S
b1000000101101100000011010110011 ]
#540
0+
#550
1+
#555
b1101 t
b110011 v
b10000001011 I
b110011 E
b100000 L
b100000 J
b1100101 B
b1100101 N
b1100101 O
b1100101 l
b1000000101101100000011010110011 ?
b1000000101101100000011010110011 H
b1000000101101100000011010110011 P
b1000000101101100000011010110011 `
b1000000101101100000011010110011 k
b11001001 )
b11001001 >
b11001001 G
b11001001 a
#560
0+
#570
1+
#576
b1101 s
b110011 u
b11001001 5
b11001001 _
b11001001 w
b1000000101101100000011010110011 A
b1000000101101100000011010110011 R
b1000000101101100000011010110011 f
b1000000101101100000011010110011 m
b1100101 *
b1100101 @
b1100101 Q
b1100101 e
b1100101 n
#580
0+
#590
1+
#597
b1101 1
b1101 q
b1101 !"
b1101 |
b110011 }
b1100101 2
b1100101 r
b1100101 ~
13
b1000000101101100000011010110011 :
b1000000101101100000011010110011 h
b1000000101101100000011010110011 {
b1100101 &
b1100101 9
b1100101 g
b1100101 z
#600
0+
b110 "
b110 0
b110 i
b110 -
#610
1+
